netmedex/__init__.py
netmedex/biocjson_parser.py
netmedex/cli.py
netmedex/cli_utils.py
netmedex/cytoscape_html_template.py
netmedex/cytoscape_js.py
netmedex/cytoscape_xgmml.py
netmedex/exceptions.py
netmedex/graph.py
netmedex/graph_data.py
netmedex/headers.py
netmedex/npmi.py
netmedex/pubtator.py
netmedex/pubtator_data.py
netmedex/pubtator_graph_data.py
netmedex/pubtator_parser.py
netmedex/stemmers.py
netmedex/types.py
netmedex/utils.py
netmedex/utils_threading.py
webapp/__init__.py
webapp/app.py
webapp/utils.py
webapp/assets/NetMedEx.png
webapp/assets/NetMedEx_ico.ico
webapp/assets/clientside_callback.js
webapp/assets/close_settings.js
webapp/assets/icon_cellline.svg
webapp/assets/icon_chemical.svg
webapp/assets/icon_config.svg
webapp/assets/icon_disease.svg
webapp/assets/icon_dnamutation.svg
webapp/assets/icon_download.svg
webapp/assets/icon_gene.svg
webapp/assets/icon_graph.svg
webapp/assets/icon_info.svg
webapp/assets/icon_proteinmutation.svg
webapp/assets/icon_search.svg
webapp/assets/icon_snp.svg
webapp/assets/icon_species.svg
webapp/assets/index.css
webapp/assets/three-dots.svg
webapp/callbacks/__init__.py
webapp/callbacks/advanced_settings.py
webapp/callbacks/export.py
webapp/callbacks/graph_settings.py
webapp/callbacks/graph_update.py
webapp/callbacks/graph_utils.py
webapp/callbacks/input_type_update.py
webapp/callbacks/pipeline.py
webapp/callbacks/upload.py
webapp/components/__init__.py
webapp/components/advanced_settings.py
webapp/components/graph.py
webapp/components/graph_info.py
webapp/components/graph_tools.py
webapp/components/sidebar.py
webapp/components/utils.py
netmedex-0.3.0.dist-info/METADATA
netmedex-0.3.0.dist-info/WHEEL
netmedex-0.3.0.dist-info/entry_points.txt
netmedex-0.3.0.dist-info/top_level.txt
netmedex-0.3.0.dist-info/RECORD
