Metadata-Version: 2.4
Name: netmedex
Version: 0.3.0
Summary: A tool to extract BioConcept entities (e.g., genes, diseases, chemicals, and species) from Pubtator3 and generate a co-mention network for interactive use.
Author-email: Zheng-Xiang Ye <r12b48005@ntu.edu.tw>
Classifier: Development Status :: 5 - Production/Stable
Classifier: Programming Language :: Python :: 3
Classifier: Programming Language :: Python :: 3.11
Classifier: Programming Language :: Python :: 3.12
Classifier: License :: OSI Approved :: MIT License
Classifier: Operating System :: OS Independent
Requires-Python: >=3.11
Requires-Dist: requests
Requires-Dist: aiohttp
Requires-Dist: aiometer
Requires-Dist: tenacity
Requires-Dist: tqdm
Requires-Dist: networkx[default]~=3.3
Requires-Dist: lxml
Requires-Dist: python-dotenv
Requires-Dist: dash[diskcache]~=2.17
Requires-Dist: dash-cytoscape~=1.0.2
Requires-Dist: dash-bootstrap_components~=1.7.1
Provides-Extra: dev
Requires-Dist: pytest~=8.3.2; extra == "dev"
Requires-Dist: pytest-xdist; extra == "dev"
Requires-Dist: pytest-cov; extra == "dev"
Requires-Dist: requests-mock; extra == "dev"
Requires-Dist: pytest-mock; extra == "dev"
Requires-Dist: ruff==0.8.0; extra == "dev"
Requires-Dist: pre-commit; extra == "dev"
Requires-Dist: mkdocs; extra == "dev"
